{
    "text_block_list": [
        {
            "name": "Daitaku Helios",
            "text": "Uwoeeeeeeeeeeeeeeeeeeee!?"
        },
        {
            "name": "Daitaku Helios",
            "text": "Kenapa kenapa～!?\nLosion-nya nggak nyerap sama sekali nih!?"
        },
        {
            "name": "Daitaku Helios",
            "text": "Yang murah nggak bisa? Bohong ah,\nselama ini kita akur-akur aja kan——!"
        },
        {
            "name": "Daitaku Helios",
            "text": "Ini kan temen setia aku?\nAku maunya kamu terus! Ayo,\nsekali lagi meresap ke kulitku dong!! Hey!!"
        },
        {
            "name": "Daitaku Helios",
            "text": "Panggung untukmu♪\nNunggu lama sampe rusak♪ Pièeee!!"
        },
        {
            "text": "Akibat kulit yang bermasalah, losion pun\njadi susah meresap pada Daitaku Helios,\ndan ia pun terus menjerit kesedihannya."
        }
    ]
}