{
  "text_block_list": [
    {
      "name": "Buena Vista",
      "text": "Ohh, jadi minggu lalu kamu pergi ke onsen\nbareng keluarga ya…! Terus besoknya juga \nsempet ke kebun binatang?"
    },
    {
      "name": "Buena Vista",
      "text": "Wah, liburannya penuh hal seru ya. Fufu.\nPasti jadi hari libur yang menyenangkan banget!"
    },
    {
      "name": "Buena Vista",
      "text": "Neh, ceritain lagi dong soal perjalanannya.\nHal yang bikin seneng atau yang bikin kaget juga boleh!"
    },
    {
      "name": "Buena Vista",
      "text": "……? Kamu ngerasa kebanyakan \nngomong soal diri sendiri…?"
    },
    {
      "name": "Buena Vista",
      "text": "Enggak kok, gak usah dipikirin!\nAku pengen denger karena aku juga\nikut seneng loh? Soalnya――"
    },
    {
      "name": "Buena Vista",
      "text": "Kalau kamu keliatan bahagia,\naku juga jadi ikut bahagia.\nSerius kok.\nJadi… lanjut cerita lagi ya?"
    }
  ]
}